statxplore/__init__.py
statxplore/__main__.py
statxplore/http_session.py
statxplore/metadata.py
statxplore/objects.py
statxplore/settings.py
statxplore/utils.py
statxplore-0.0.1.post1.dist-info/LICENSE.txt
statxplore-0.0.1.post1.dist-info/METADATA
statxplore-0.0.1.post1.dist-info/WHEEL
statxplore-0.0.1.post1.dist-info/entry_points.txt
statxplore-0.0.1.post1.dist-info/top_level.txt
statxplore-0.0.1.post1.dist-info/RECORD
