Metadata-Version: 2.1
Name: statxplore
Version: 0.0.1.post1
Summary: This is a data harvester for the Department for Work and Pensions Stat-Explore
Home-page: https://github.com/urban-flows/stat-xplore
Author: Joe Heffer
Author-email: j.heffer@sheffield.ac.uk
License: UNKNOWN
Project-URL: Bug Tracker, https://github.com/urban-flows/stat-xplore/issues
Platform: UNKNOWN
Classifier: Programming Language :: Python :: 3
Classifier: License :: OSI Approved :: MIT License
Classifier: Operating System :: OS Independent
Requires-Python: >=3.6
License-File: LICENSE.txt
Requires-Dist: requests
